app/__init__.py
app/asgi.py
app/router.py
app/config/__init__.py
app/config/config.py
app/models/__init__.py
app/models/const.py
app/models/exception.py
app/models/schema.py
app/services/__init__.py
app/services/llm.py
app/services/material.py
app/services/subtitle.py
app/services/task.py
app/services/video.py
app/services/voice.py
MoneyPrinterTurbo-1.4.5.dist-info/LICENSE
MoneyPrinterTurbo-1.4.5.dist-info/METADATA
MoneyPrinterTurbo-1.4.5.dist-info/WHEEL
MoneyPrinterTurbo-1.4.5.dist-info/top_level.txt
MoneyPrinterTurbo-1.4.5.dist-info/RECORD
